<annotation>
  <folder>images</folder>
  <filename>b4d2780e-candy_120.jpg</filename>
  <path>b4d2780e-candy_120.jpg</path>
  <source>
    <database>Unknown</database>
  </source>
  <size>
    <width>1280</width>
    <height>720</height>
    <depth>3</depth>
  </size>
  <segmented>0</segmented>
  <object>
    <name>three_musketeers</name>
    <pose>Unspecified</pose>
    <truncated>0</truncated>
    <difficult>0</difficult>
    <bndbox>
      <xmin>177</xmin>
      <ymin>181</ymin>
      <xmax>262</xmax>
      <ymax>344</ymax>
    </bndbox>
  </object>
</annotation>
