<annotation>
  <folder>images</folder>
  <filename>e4b09525-candy_7.jpg</filename>
  <path>e4b09525-candy_7.jpg</path>
  <source>
    <database>Unknown</database>
  </source>
  <size>
    <width>1920</width>
    <height>1080</height>
    <depth>3</depth>
  </size>
  <segmented>0</segmented>
  <object>
    <name>airheads</name>
    <pose>Unspecified</pose>
    <truncated>0</truncated>
    <difficult>0</difficult>
    <bndbox>
      <xmin>547</xmin>
      <ymin>337</ymin>
      <xmax>678</xmax>
      <ymax>637</ymax>
    </bndbox>
  </object>
  <object>
    <name>airheads</name>
    <pose>Unspecified</pose>
    <truncated>0</truncated>
    <difficult>0</difficult>
    <bndbox>
      <xmin>877</xmin>
      <ymin>242</ymin>
      <xmax>1192</xmax>
      <ymax>408</ymax>
    </bndbox>
  </object>
  <object>
    <name>starbust</name>
    <pose>Unspecified</pose>
    <truncated>0</truncated>
    <difficult>0</difficult>
    <bndbox>
      <xmin>693</xmin>
      <ymin>447</ymin>
      <xmax>874</xmax>
      <ymax>717</ymax>
    </bndbox>
  </object>
  <object>
    <name>three_musketeers</name>
    <pose>Unspecified</pose>
    <truncated>0</truncated>
    <difficult>0</difficult>
    <bndbox>
      <xmin>961</xmin>
      <ymin>544</ymin>
      <xmax>1207</xmax>
      <ymax>825</ymax>
    </bndbox>
  </object>
</annotation>
