<annotation>
  <folder>images</folder>
  <filename>ffcfd581-candy_52.jpg</filename>
  <path>ffcfd581-candy_52.jpg</path>
  <source>
    <database>Unknown</database>
  </source>
  <size>
    <width>1280</width>
    <height>720</height>
    <depth>3</depth>
  </size>
  <segmented>0</segmented>
  <object>
    <name>snickers</name>
    <pose>Unspecified</pose>
    <truncated>0</truncated>
    <difficult>0</difficult>
    <bndbox>
      <xmin>469</xmin>
      <ymin>320</ymin>
      <xmax>641</xmax>
      <ymax>398</ymax>
    </bndbox>
  </object>
  <object>
    <name>milky_way</name>
    <pose>Unspecified</pose>
    <truncated>0</truncated>
    <difficult>0</difficult>
    <bndbox>
      <xmin>265</xmin>
      <ymin>278</ymin>
      <xmax>417</xmax>
      <ymax>455</ymax>
    </bndbox>
  </object>
  <object>
    <name>airheads</name>
    <pose>Unspecified</pose>
    <truncated>0</truncated>
    <difficult>0</difficult>
    <bndbox>
      <xmin>307</xmin>
      <ymin>136</ymin>
      <xmax>508</xmax>
      <ymax>237</ymax>
    </bndbox>
  </object>
  <object>
    <name>nerds</name>
    <pose>Unspecified</pose>
    <truncated>0</truncated>
    <difficult>0</difficult>
    <bndbox>
      <xmin>529</xmin>
      <ymin>161</ymin>
      <xmax>638</xmax>
      <ymax>262</ymax>
    </bndbox>
  </object>
  <object>
    <name>three_musketeers</name>
    <pose>Unspecified</pose>
    <truncated>0</truncated>
    <difficult>0</difficult>
    <bndbox>
      <xmin>624</xmin>
      <ymin>135</ymin>
      <xmax>738</xmax>
      <ymax>305</ymax>
    </bndbox>
  </object>
</annotation>
